{
  "id": "f0f1f70a-2f1f-4a8c-b064-bd4dd7a5e052",
  "prevId": "a0a39d6e-ba7a-454f-a46b-57f466301fec",
  "version": "7",
  "dialect": "postgresql",
  "tables": {
    "public.enrolled_students": {
      "name": "enrolled_students",
      "schema": "",
      "columns": {
        "enrolled_student_id": {
          "name": "enrolled_student_id",
          "type": "serial",
          "primaryKey": true,
          "notNull": true
        },
        "student_id": {
          "name": "student_id",
          "type": "integer",
          "primaryKey": false,
          "notNull": true
        },
        "grade_level_id": {
          "name": "grade_level_id",
          "type": "integer",
          "primaryKey": false,
          "notNull": true
        },
        "school_id": {
          "name": "school_id",
          "type": "integer",
          "primaryKey": false,
          "notNull": false
        },
        "section_id": {
          "name": "section_id",
          "type": "integer",
          "primaryKey": false,
          "notNull": false
        },
        "is_id_paid": {
          "name": "is_id_paid",
          "type": "boolean",
          "primaryKey": false,
          "notNull": false
        },
        "school_year": {
          "name": "school_year",
          "type": "varchar",
          "primaryKey": false,
          "notNull": false
        }
      },
      "indexes": {},
      "foreignKeys": {},
      "compositePrimaryKeys": {},
      "uniqueConstraints": {}
    },
    "public.grade_levels": {
      "name": "grade_levels",
      "schema": "",
      "columns": {
        "grade_level_id": {
          "name": "grade_level_id",
          "type": "serial",
          "primaryKey": true,
          "notNull": true
        },
        "description": {
          "name": "description",
          "type": "text",
          "primaryKey": false,
          "notNull": false
        },
        "icon": {
          "name": "icon",
          "type": "varchar",
          "primaryKey": false,
          "notNull": false
        },
        "id_template": {
          "name": "id_template",
          "type": "integer",
          "primaryKey": false,
          "notNull": false
        },
        "level_name": {
          "name": "level_name",
          "type": "varchar",
          "primaryKey": false,
          "notNull": false
        },
        "order_number": {
          "name": "order_number",
          "type": "integer",
          "primaryKey": false,
          "notNull": false
        },
        "school_id": {
          "name": "school_id",
          "type": "integer",
          "primaryKey": false,
          "notNull": false
        }
      },
      "indexes": {},
      "foreignKeys": {},
      "compositePrimaryKeys": {},
      "uniqueConstraints": {}
    },
    "public.sections": {
      "name": "sections",
      "schema": "",
      "columns": {
        "section_id": {
          "name": "section_id",
          "type": "serial",
          "primaryKey": true,
          "notNull": true
        },
        "course_tvl": {
          "name": "course_tvl",
          "type": "varchar(50)",
          "primaryKey": false,
          "notNull": false
        },
        "created_by": {
          "name": "created_by",
          "type": "varchar",
          "primaryKey": false,
          "notNull": false
        },
        "created_date": {
          "name": "created_date",
          "type": "timestamp",
          "primaryKey": false,
          "notNull": false,
          "default": "CURRENT_TIMESTAMP"
        },
        "grade_level_id": {
          "name": "grade_level_id",
          "type": "integer",
          "primaryKey": false,
          "notNull": false
        },
        "school_id": {
          "name": "school_id",
          "type": "integer",
          "primaryKey": false,
          "notNull": false
        },
        "school_year": {
          "name": "school_year",
          "type": "varchar(50)",
          "primaryKey": false,
          "notNull": false
        },
        "section_name": {
          "name": "section_name",
          "type": "varchar(50)",
          "primaryKey": false,
          "notNull": false
        },
        "track_and_strand": {
          "name": "track_and_strand",
          "type": "varchar(50)",
          "primaryKey": false,
          "notNull": false
        },
        "updated_by": {
          "name": "updated_by",
          "type": "varchar",
          "primaryKey": false,
          "notNull": false
        },
        "updated_date": {
          "name": "updated_date",
          "type": "timestamp",
          "primaryKey": false,
          "notNull": false,
          "default": "CURRENT_TIMESTAMP"
        }
      },
      "indexes": {},
      "foreignKeys": {},
      "compositePrimaryKeys": {},
      "uniqueConstraints": {}
    },
    "public.students": {
      "name": "students",
      "schema": "",
      "columns": {
        "id": {
          "name": "id",
          "type": "serial",
          "primaryKey": true,
          "notNull": true
        },
        "active": {
          "name": "active",
          "type": "integer",
          "primaryKey": false,
          "notNull": false
        },
        "barangay": {
          "name": "barangay",
          "type": "varchar",
          "primaryKey": false,
          "notNull": false
        },
        "birth_date": {
          "name": "birth_date",
          "type": "date",
          "primaryKey": false,
          "notNull": false
        },
        "city_municipality": {
          "name": "city_municipality",
          "type": "varchar",
          "primaryKey": false,
          "notNull": false
        },
        "ethnic_group": {
          "name": "ethnic_group",
          "type": "varchar",
          "primaryKey": false,
          "notNull": false
        },
        "father_name": {
          "name": "father_name",
          "type": "varchar",
          "primaryKey": false,
          "notNull": false
        },
        "mother_name": {
          "name": "mother_name",
          "type": "varchar",
          "primaryKey": false,
          "notNull": false
        },
        "first_name": {
          "name": "first_name",
          "type": "varchar",
          "primaryKey": false,
          "notNull": false
        },
        "last_name": {
          "name": "last_name",
          "type": "varchar",
          "primaryKey": false,
          "notNull": false
        },
        "ext_name": {
          "name": "ext_name",
          "type": "varchar",
          "primaryKey": false,
          "notNull": false
        },
        "middle_name": {
          "name": "middle_name",
          "type": "varchar",
          "primaryKey": false,
          "notNull": false
        },
        "full_name": {
          "name": "full_name",
          "type": "varchar",
          "primaryKey": false,
          "notNull": false
        },
        "gender": {
          "name": "gender",
          "type": "varchar(10)",
          "primaryKey": false,
          "notNull": false
        },
        "grade_level": {
          "name": "grade_level",
          "type": "varchar(50)",
          "primaryKey": false,
          "notNull": false
        },
        "guardian_name": {
          "name": "guardian_name",
          "type": "varchar",
          "primaryKey": false,
          "notNull": false
        },
        "guardian_relationship": {
          "name": "guardian_relationship",
          "type": "varchar(50)",
          "primaryKey": false,
          "notNull": false
        },
        "learning_modality": {
          "name": "learning_modality",
          "type": "varchar",
          "primaryKey": false,
          "notNull": false
        },
        "lrn": {
          "name": "lrn",
          "type": "varchar",
          "primaryKey": false,
          "notNull": false
        },
        "mother_tongue": {
          "name": "mother_tongue",
          "type": "varchar",
          "primaryKey": false,
          "notNull": false
        },
        "parent_mobile_number": {
          "name": "parent_mobile_number",
          "type": "varchar(20)",
          "primaryKey": false,
          "notNull": false
        },
        "province": {
          "name": "province",
          "type": "varchar",
          "primaryKey": false,
          "notNull": false
        },
        "religion": {
          "name": "religion",
          "type": "varchar",
          "primaryKey": false,
          "notNull": false
        },
        "remarks": {
          "name": "remarks",
          "type": "text",
          "primaryKey": false,
          "notNull": false
        },
        "school_id": {
          "name": "school_id",
          "type": "integer",
          "primaryKey": false,
          "notNull": false
        },
        "section_id": {
          "name": "section_id",
          "type": "integer",
          "primaryKey": false,
          "notNull": false
        },
        "street_address": {
          "name": "street_address",
          "type": "varchar",
          "primaryKey": false,
          "notNull": false
        },
        "enrollment_id": {
          "name": "enrollment_id",
          "type": "integer",
          "primaryKey": false,
          "notNull": false
        },
        "img_url": {
          "name": "img_url",
          "type": "text",
          "primaryKey": false,
          "notNull": false
        },
        "qrcode": {
          "name": "qrcode",
          "type": "text",
          "primaryKey": false,
          "notNull": false
        }
      },
      "indexes": {},
      "foreignKeys": {},
      "compositePrimaryKeys": {},
      "uniqueConstraints": {}
    }
  },
  "enums": {},
  "schemas": {},
  "_meta": {
    "columns": {},
    "schemas": {},
    "tables": {}
  }
}